causara/APACHE_LICENSE
causara/BSD 3-Clause License
causara/COMMON_PUBLIC_LICENSE
causara/ECLIPSE_LICENSE
causara/LICENSE.txt
causara/README.md
causara/__init__.py
causara/checksums.p
causara/Demos/Cell_tower.cp310-win_amd64.pyd
causara/Demos/Cell_tower.cp311-win_amd64.pyd
causara/Demos/Cell_tower.cp312-win_amd64.pyd
causara/Demos/Cell_tower.cp39-win_amd64.pyd
causara/Demos/Cell_tower.cpython-310-darwin.so
causara/Demos/Cell_tower.cpython-310-x86_64-linux-gnu.so
causara/Demos/Cell_tower.cpython-311-darwin.so
causara/Demos/Cell_tower.cpython-311-x86_64-linux-gnu.so
causara/Demos/Cell_tower.cpython-312-darwin.so
causara/Demos/Cell_tower.cpython-312-x86_64-linux-gnu.so
causara/Demos/Cell_tower.cpython-39-darwin.so
causara/Demos/Cell_tower.cpython-39-x86_64-linux-gnu.so
causara/Demos/DistanceMatrix.cp310-win_amd64.pyd
causara/Demos/DistanceMatrix.cp311-win_amd64.pyd
causara/Demos/DistanceMatrix.cp312-win_amd64.pyd
causara/Demos/DistanceMatrix.cp39-win_amd64.pyd
causara/Demos/DistanceMatrix.cpython-310-darwin.so
causara/Demos/DistanceMatrix.cpython-310-x86_64-linux-gnu.so
causara/Demos/DistanceMatrix.cpython-311-darwin.so
causara/Demos/DistanceMatrix.cpython-311-x86_64-linux-gnu.so
causara/Demos/DistanceMatrix.cpython-312-darwin.so
causara/Demos/DistanceMatrix.cpython-312-x86_64-linux-gnu.so
causara/Demos/DistanceMatrix.cpython-39-darwin.so
causara/Demos/DistanceMatrix.cpython-39-x86_64-linux-gnu.so
causara/Demos/Molecules.cp310-win_amd64.pyd
causara/Demos/Molecules.cp311-win_amd64.pyd
causara/Demos/Molecules.cp312-win_amd64.pyd
causara/Demos/Molecules.cp39-win_amd64.pyd
causara/Demos/Molecules.cpython-310-darwin.so
causara/Demos/Molecules.cpython-310-x86_64-linux-gnu.so
causara/Demos/Molecules.cpython-311-darwin.so
causara/Demos/Molecules.cpython-311-x86_64-linux-gnu.so
causara/Demos/Molecules.cpython-312-darwin.so
causara/Demos/Molecules.cpython-312-x86_64-linux-gnu.so
causara/Demos/Molecules.cpython-39-darwin.so
causara/Demos/Molecules.cpython-39-x86_64-linux-gnu.so
causara-3.4.6.dist-info/licenses/LICENSE.txt
causara-3.4.6.dist-info/METADATA
causara-3.4.6.dist-info/WHEEL
causara-3.4.6.dist-info/top_level.txt
causara-3.4.6.dist-info/RECORD
