Metadata-Version: 2.4
Name: causara
Version: 3.4.6
Summary: Causara is a Python package designed for advanced surrogate modeling of optimization problems. For more information, visit https://www.causara.com.
Home-page: https://www.causara.com
Author: causara UG
Author-email: support@causara.com
License: Proprietary
Classifier: Programming Language :: Python :: 3
Classifier: License :: Other/Proprietary License
Classifier: Operating System :: OS Independent
Requires-Python: >=3.9, <3.13
License-File: LICENSE.txt
Requires-Dist: torch
Requires-Dist: bcrypt
Requires-Dist: numpy<2
Requires-Dist: scipy
Requires-Dist: gurobipy
Requires-Dist: pandas
Requires-Dist: openpyxl
Requires-Dist: reportlab
Requires-Dist: psutil
Requires-Dist: sympy
Requires-Dist: tqdm
Requires-Dist: pywebview
Requires-Dist: qtpy; sys_platform == "linux"
Requires-Dist: PyQt5; sys_platform == "linux"
Requires-Dist: PyQtWebEngine; sys_platform == "linux"
Requires-Dist: cefpython3; sys_platform != "linux" and sys_platform != "darwin"
Requires-Dist: rdkit
Requires-Dist: matplotlib
Requires-Dist: folium
Requires-Dist: orjson
Requires-Dist: pyyaml
Requires-Dist: pywin32; sys_platform == "win32"
Requires-Dist: pyomo
Requires-Dist: pyscipopt
Requires-Dist: highspy
Requires-Dist: numba
Dynamic: author
Dynamic: author-email
Dynamic: classifier
Dynamic: description
Dynamic: description-content-type
Dynamic: home-page
Dynamic: license
Dynamic: license-file
Dynamic: requires-dist
Dynamic: requires-python
Dynamic: summary
